Workbook

Sheet Sheet1
A1: 【前提①】売上高 成長率（対前年） | C1: 0.015 | D1: 0.015 | E1: 0.04 | F1: 0.04 | G1: 0.04 | H1: 0.04 | I1: 0.04
A2: 【前提②】売上原価率（対売上高） | B2: =B8/B7 -> 0.90588833 | C2: 0.9057 | D2: 0.905 | E2: 0.9025 | F2: 0.9 | G2: 0.8975 | H2: 0.8945 | I2: 0.8915
A3: 【前提③】その他販管費率（対売上高） | B3: =B28/B7 -> 0.047702148 | C3: 0.0477 | D3: 0.0477 | E3: 0.0477 | F3: 0.0477 | G3: 0.0477 | H3: 0.0477 | I3: 0.0477
A4: 【前提④】1人当たり賃上げ率（対前年） | C4: 0.03 | D4: 0.03 | E4: 0.035 | F4: 0.035 | G4: 0.035 | H4: 0.035 | I4: 0.035
A5: 【前提⑤】本事業設備の減価償却費 | C5: 0 | D5: 0 | E5: 9200000 | F5: 9200000 | G5: 9200000 | H5: 9200000 | I5: 9200000
A6: 収支詳細 | B6: 直近年度 2026年3月 | C6: 進行期 2027年3月 | D6: 基準年度 2028年3月 | E6: 1年目 2029年3月 | F6: 2年目 2030年3月 | G6: 3年目 2031年3月 | H6: 4年目（目標値） 2032年3月 | I6: 5年目（目標値） 2033年3月 | J6: ※事業計画期間は3年。4・5年目は目標値として策定（よくあるご質問No.8：目標値は5年目まで必要）。別紙４のJ・K列へ転記。
A7: ①売上高 | B7: =人件費・給与支給総額!J4 -> 11168904537 | C7: =ROUND(B7*(1+C$1),0) -> 11336438105 | D7: =ROUND(C7*(1+D$1),0) -> 11506484677 | E7: =ROUND(D7*(1+E$1),0) -> 11966744064 | F7: =ROUND(E7*(1+F$1),0) -> 12445413827 | G7: =ROUND(F7*(1+G$1),0) -> 12943230380 | H7: =ROUND(G7*(1+H$1),0) -> 13460959595 | I7: =ROUND(H7*(1+I$1),0) -> 13999397979
A8: 売上原価 | B8: =人件費・給与支給総額!J6 -> 10117780260 | C8: =ROUND(C7*C$2,0) -> 10267411992 | D8: =ROUND(D7*D$2,0) -> 10413368633 | E8: =ROUND(E7*E$2,0) -> 10799986518 | F8: =ROUND(F7*F$2,0) -> 11200872444 | G8: =ROUND(G7*G$2,0) -> 11616549266 | H8: =ROUND(H7*H$2,0) -> 12040828358 | I8: =ROUND(I7*I$2,0) -> 12480463298
A9: （原価率） | B9: =B8/B7 -> 0.90588833 | C9: =C8/C7 -> 0.9057 | D9: =D8/D7 -> 0.905 | E9: =E8/E7 -> 0.9025 | F9: =F8/F7 -> 0.9 | G9: =G8/G7 -> 0.8975 | H9: =H8/H7 -> 0.8945 | I9: =I8/I7 -> 0.8915
A10: └うち人件費 | B10: =人件費・給与支給総額!C10 -> 733251723 | C10: =ROUND(C33*$B$10/$B$33,0) -> 738217735 | D10: =ROUND(D33*$B$10/$B$33,0) -> 775037872 | E10: =ROUND(E33*$B$10/$B$33,0) -> 813002830 | F10: =ROUND(F33*$B$10/$B$33,0) -> 857041779 | G10: =ROUND(G33*$B$10/$B$33,0) -> 898766289 | H10: =ROUND(H33*$B$10/$B$33,0) -> 947034354 | I10: =ROUND(I33*$B$10/$B$33,0) -> 992861369
A11: └うち役員給与支給総額 | B11: =人件費・給与支給総額!C11 -> 0 | C11: =C12+C13 -> 0 | D11: =D12+D13 -> 0 | E11: =E12+E13 -> 0 | F11: =F12+F13 -> 0 | G11: =G12+G13 -> 0 | H11: =H12+H13 -> 0 | I11: =I12+I13 -> 0
A12: └うち賞与 | B12: =人件費・給与支給総額!C12 -> 0 | C12: =B12 -> 0 | D12: =C12 -> 0 | E12: =D12 -> 0 | F12: =E12 -> 0 | G12: =F12 -> 0 | H12: =G12 -> 0 | I12: =H12 -> 0
A13: └うち給与・賃金 | B13: =人件費・給与支給総額!C13 -> 0 | C13: =B13 -> 0 | D13: =C13 -> 0 | E13: =D13 -> 0 | F13: =E13 -> 0 | G13: =F13 -> 0 | H13: =G13 -> 0 | I13: =H13 -> 0
A14: └うち従業員給与支給総額 | B14: =人件費・給与支給総額!C14 -> 620349460 | C14: =C15+C16 -> 624839282 | D14: =D15+D16 -> 658128742 | E14: =E15+E16 -> 692453246 | F14: =F15+F16 -> 732269307 | G14: =G15+G16 -> 769992862 | H14: =H15+H16 -> 813632509 | I14: =I15+I16 -> 855065180
A15: └うち賞与 | B15: =人件費・給与支給総額!C15 -> 153907318 | C15: =ROUND(B15*(1+C$4)*C$42/B$42,0) -> 155021233 | D15: =ROUND(C15*(1+D$4)*D$42/C$42,0) -> 163280274 | E15: =ROUND(D15*(1+E$4)*E$42/D$42,0) -> 171796107 | F15: =ROUND(E15*(1+F$4)*F$42/E$42,0) -> 181674383 | G15: =ROUND(F15*(1+G$4)*G$42/F$42,0) -> 191033513 | H15: =ROUND(G15*(1+H$4)*H$42/G$42,0) -> 201860412 | I15: =ROUND(H15*(1+I$4)*I$42/H$42,0) -> 212139765
A16: └うち給与・賃金 | B16: =人件費・給与支給総額!C16 -> 466442142 | C16: =ROUND(B16*(1+C$4)*C$42/B$42,0) -> 469818049 | D16: =ROUND(C16*(1+D$4)*D$42/C$42,0) -> 494848468 | E16: =ROUND(D16*(1+E$4)*E$42/D$42,0) -> 520657139 | F16: =ROUND(E16*(1+F$4)*F$42/E$42,0) -> 550594924 | G16: =ROUND(F16*(1+G$4)*G$42/F$42,0) -> 578959349 | H16: =ROUND(G16*(1+H$4)*H$42/G$42,0) -> 611772097 | I16: =ROUND(H16*(1+I$4)*I$42/H$42,0) -> 642925415
A17: └うち減価償却費 | B17: =人件費・給与支給総額!J11 -> 274032833 | C17: =$B$17+C5 -> 274032833 | D17: =$B$17+D5 -> 274032833 | E17: =$B$17+E5 -> 283232833 | F17: =$B$17+F5 -> 283232833 | G17: =$B$17+G5 -> 283232833 | H17: =$B$17+H5 -> 283232833 | I17: =$B$17+I5 -> 283232833
A18: 粗利 | B18: =B7-B8 -> 1051124277 | C18: =C7-C8 -> 1069026113 | D18: =D7-D8 -> 1093116044 | E18: =E7-E8 -> 1166757546 | F18: =F7-F8 -> 1244541383 | G18: =G7-G8 -> 1326681114 | H18: =H7-H8 -> 1420131237 | I18: =I7-I8 -> 1518934681
A19: 販管費 | B19: 846301227 | C19: =C20+C27+C28 -> 856223758 | D19: =D20+D27+D28 -> 878831451 | E19: =E20+E27+E28 -> 915733024 | F19: =F20+F27+F28 -> 955904165 | G19: =G20+G27+G28 -> 996077390 | H19: =H20+H27+H28 -> 1039776714 | I19: =I20+I27+I28 -> 1083502800
A20: └うち人件費 | B20: =人件費・給与支給総額!C28 -> 288688854 | C20: =C33-C10 -> 290644025 | D20: =D33-D10 -> 305140497 | E20: =E33-E10 -> 320087697 | F20: =F33-F10 -> 337426290 | G20: =G33-G10 -> 353853666 | H20: =H33-H10 -> 372857306 | I20: =I33-I10 -> 390899881
A21: └うち役員給与支給総額 | B21: =人件費・給与支給総額!C29 -> 65655000 | C21: =C22+C23 -> 65655000 | D21: =D22+D23 -> 65655000 | E21: =E22+E23 -> 65655000 | F21: =F22+F23 -> 65655000 | G21: =G22+G23 -> 65655000 | H21: =H22+H23 -> 65655000 | I21: =I22+I23 -> 65655000
A22: └うち賞与 | B22: =人件費・給与支給総額!C30 -> 0 | C22: =B22 -> 0 | D22: =C22 -> 0 | E22: =D22 -> 0 | F22: =E22 -> 0 | G22: =F22 -> 0 | H22: =G22 -> 0 | I22: =H22 -> 0
A23: └うち給与・賃金 | B23: =人件費・給与支給総額!C31 -> 65655000 | C23: =B23 -> 65655000 | D23: =C23 -> 65655000 | E23: =D23 -> 65655000 | F23: =E23 -> 65655000 | G23: =F23 -> 65655000 | H23: =G23 -> 65655000 | I23: =H23 -> 65655000
A24: └うち従業員給与支給総額 | B24: =人件費・給与支給総額!C32 -> 173507534 | C24: =C25+C26 -> 174763306 | D24: =D25+D26 -> 184074142 | E24: =E25+E26 -> 193674473 | F24: =F25+F26 -> 204810756 | G24: =G25+G26 -> 215361778 | H24: =H25+H26 -> 227567492 | I24: =I25+I26 -> 239155929
A25: └うち賞与 | B25: =人件費・給与支給総額!C33 -> 50163729 | C25: =ROUND(B25*(1+C$4)*C$42/B$42,0) -> 50526792 | D25: =ROUND(C25*(1+D$4)*D$42/C$42,0) -> 53218700 | E25: =ROUND(D25*(1+E$4)*E$42/D$42,0) -> 55994305 | F25: =ROUND(E25*(1+F$4)*F$42/E$42,0) -> 59213978 | G25: =ROUND(F25*(1+G$4)*G$42/F$42,0) -> 62264443 | H25: =ROUND(G25*(1+H$4)*H$42/G$42,0) -> 65793305 | I25: =ROUND(H25*(1+I$4)*I$42/H$42,0) -> 69143703
A26: └うち給与・賃金 | B26: =人件費・給与支給総額!C34 -> 123343805 | C26: =ROUND(B26*(1+C$4)*C$42/B$42,0) -> 124236514 | D26: =ROUND(C26*(1+D$4)*D$42/C$42,0) -> 130855442 | E26: =ROUND(D26*(1+E$4)*E$42/D$42,0) -> 137680168 | F26: =ROUND(E26*(1+F$4)*F$42/E$42,0) -> 145596778 | G26: =ROUND(F26*(1+G$4)*G$42/F$42,0) -> 153097335 | H26: =ROUND(G26*(1+H$4)*H$42/G$42,0) -> 161774187 | I26: =ROUND(H26*(1+I$4)*I$42/H$42,0) -> 170012226
A27: └うち減価償却費 | B27: =人件費・給与支給総額!J12 -> 24831635 | C27: =$B$27 -> 24831635 | D27: =$B$27 -> 24831635 | E27: =$B$27 -> 24831635 | F27: =$B$27 -> 24831635 | G27: =$B$27 -> 24831635 | H27: =$B$27 -> 24831635 | I27: =$B$27 -> 24831635
A28: └その他販管費 | B28: =B19-B20-B27 -> 532780738 | C28: =ROUND(C7*C$3,0) -> 540748098 | D28: =ROUND(D7*D$3,0) -> 548859319 | E28: =ROUND(E7*E$3,0) -> 570813692 | F28: =ROUND(F7*F$3,0) -> 593646240 | G28: =ROUND(G7*G$3,0) -> 617392089 | H28: =ROUND(H7*H$3,0) -> 642087773 | I28: =ROUND(I7*I$3,0) -> 667771284
A29: （その他販管費率：対売上） | B29: =B28/B7 -> 0.047702148 | C29: =C28/C7 -> 0.0477 | D29: =D28/D7 -> 0.0477 | E29: =E28/E7 -> 0.0477 | F29: =F28/F7 -> 0.0477 | G29: =G28/G7 -> 0.0477 | H29: =H28/H7 -> 0.0477 | I29: =I28/I7 -> 0.0477
A30: ②営業利益 | B30: =B18-B19 -> 204823050 | C30: =C18-C19 -> 212802355 | D30: =D18-D19 -> 214284593 | E30: =E18-E19 -> 251024522 | F30: =F18-F19 -> 288637218 | G30: =G18-G19 -> 330603724 | H30: =H18-H19 -> 380354523 | I30: =I18-I19 -> 435431881
A31: （営業利益率） | B31: =B30/B7 -> 0.018338687 | C31: =C30/C7 -> 0.018771536 | D31: =D30/D7 -> 0.018622942 | E31: =E30/E7 -> 0.020976844 | F31: =F30/F7 -> 0.023192256 | G31: =G30/G7 -> 0.025542598 | H31: =H30/H7 -> 0.028256122 | I31: =I30/I7 -> 0.031103615
A32: ③経常利益 | B32: 205886748 | C32: =C30+($B$32-$B$30) -> 213866053 | D32: =D30+($B$32-$B$30) -> 215348291 | E32: =E30+($B$32-$B$30) -> 252088220 | F32: =F30+($B$32-$B$30) -> 289700916 | G32: =G30+($B$32-$B$30) -> 331667422 | H32: =H30+($B$32-$B$30) -> 381418221 | I32: =I30+($B$32-$B$30) -> 436495579
A33: ④人件費計 | B33: =B10+B20 -> 1021940577 | C33: =ROUND(C48*C42+C34,0) -> 1028861760 | D33: =ROUND(D48*D42+D34,0) -> 1080178369 | E33: =ROUND(E48*E42+E34,0) -> 1133090527 | F33: =ROUND(F48*F42+F34,0) -> 1194468069 | G33: =ROUND(G48*G42+G34,0) -> 1252619955 | H33: =ROUND(H48*H42+H34,0) -> 1319891660 | I33: =ROUND(I48*I42+I34,0) -> 1383761250
A34: └役員報酬給与支給総額 | B34: =B11+B21 -> 65655000 | C34: =C11+C21 -> 65655000 | D34: =D11+D21 -> 65655000 | E34: =E11+E21 -> 65655000 | F34: =F11+F21 -> 65655000 | G34: =G11+G21 -> 65655000 | H34: =H11+H21 -> 65655000 | I34: =I11+I21 -> 65655000
A35: └うち賞与 | B35: =B12+B22 -> 0 | C35: =C12+C22 -> 0 | D35: =D12+D22 -> 0 | E35: =E12+E22 -> 0 | F35: =F12+F22 -> 0 | G35: =G12+G22 -> 0 | H35: =H12+H22 -> 0 | I35: =I12+I22 -> 0
A36: └うち給与・賃金 | B36: =B13+B23 -> 65655000 | C36: =C13+C23 -> 65655000 | D36: =D13+D23 -> 65655000 | E36: =E13+E23 -> 65655000 | F36: =F13+F23 -> 65655000 | G36: =G13+G23 -> 65655000 | H36: =H13+H23 -> 65655000 | I36: =I13+I23 -> 65655000
A37: └従業員給与支給総額 | B37: =B14+B24 -> 793856994 | C37: =C14+C24 -> 799602588 | D37: =D14+D24 -> 842202884 | E37: =E14+E24 -> 886127719 | F37: =F14+F24 -> 937080063 | G37: =G14+G24 -> 985354640 | H37: =H14+H24 -> 1041200001 | I37: =I14+I24 -> 1094221109
A38: └うち賞与 | B38: =B15+B25 -> 204071047 | C38: =C15+C25 -> 205548025 | D38: =D15+D25 -> 216498974 | E38: =E15+E25 -> 227790412 | F38: =F15+F25 -> 240888361 | G38: =G15+G25 -> 253297956 | H38: =H15+H25 -> 267653717 | I38: =I15+I25 -> 281283468
A39: └うち給与・賃金 | B39: =B16+B26 -> 589785947 | C39: =C16+C26 -> 594054563 | D39: =D16+D26 -> 625703910 | E39: =E16+E26 -> 658337307 | F39: =F16+F26 -> 696191702 | G39: =G16+G26 -> 732056684 | H39: =H16+H26 -> 773546284 | I39: =I16+I26 -> 812937641
A40: ⑤減価償却費 | B40: =B17+B27 -> 298864468 | C40: =C17+C27 -> 298864468 | D40: =D17+D27 -> 298864468 | E40: =E17+E27 -> 308064468 | F40: =F17+F27 -> 308064468 | G40: =G17+G27 -> 308064468 | H40: =H17+H27 -> 308064468 | I40: =I17+I27 -> 308064468
A41: 付加価値額 （②＋④＋⑤） | B41: =B30+B33+B40 -> 1525628095 | C41: =C30+C33+C40 -> 1540528583 | D41: =D30+D33+D40 -> 1593327430 | E41: =E30+E33+E40 -> 1692179517 | F41: =F30+F33+F40 -> 1791169755 | G41: =G30+G33+G40 -> 1891288147 | H41: =H30+H33+H40 -> 2008310651 | I41: =I30+I33+I40 -> 2127257599
A42: 従業員人数（常勤） | B42: 181 | C42: 177 | D42: 181 | E42: 184 | F42: 188 | G42: 191 | H42: 195 | I42: 198
A43: A:全月分の給与等の支給を受けた従業員の給与支給総額 | B43: 717003483 | C43: =C45*C44 -> 787608582 | D43: =D45*D44 -> 829735675 | E43: =E45*E44 -> 873184880 | F43: =F45*F44 -> 923577636 | G43: =G45*G44 -> 971350746 | H43: =H45*H44 -> 1026607530 | I43: =I45*I44 -> 1079101188
A44: B：全月分の給与等の支給を受けた従業員数 | B44: 166 | C44: =C42 -> 177 | D44: =D42 -> 181 | E44: =E42 -> 184 | F44: =F42 -> 188 | G44: =G42 -> 191 | H44: =H42 -> 195 | I44: =I42 -> 198
A45: 従業員一人当たり給与支給総額 （A÷B） | B45: =B43/B44 -> 4319298.1 | C45: =ROUNDDOWN(B45*(1+C$4)*(1+$B$49),0) -> 4449766 | D45: =ROUNDDOWN(C45*(1+D$4)*(1+$B$49),0) -> 4584175 | E45: =ROUNDDOWN(D45*(1+E$4)*(1+$B$49),0) -> 4745570 | F45: =ROUNDDOWN(E45*(1+F$4)*(1+$B$49),0) -> 4912647 | G45: =ROUNDDOWN(F45*(1+G$4)*(1+$B$49),0) -> 5085606 | H45: =ROUNDDOWN(G45*(1+H$4)*(1+$B$49),0) -> 5264654 | I45: =ROUNDDOWN(H45*(1+I$4)*(1+$B$49),0) -> 5450006
A46: 役員数 | B46: 7 | C46: 7 | D46: =C46 -> 7 | E46: =D46 -> 7 | F46: =E46 -> 7 | G46: =F46 -> 7 | H46: =G46 -> 7 | I46: =H46 -> 7
A47: 全体の給与支給総額計 | B47: =B34+B37 -> 859511994 | C47: =C34+C37 -> 865257588 | D47: =D34+D37 -> 907857884 | E47: =E34+E37 -> 951782719 | F47: =F34+F37 -> 1002735063 | G47: =G34+G37 -> 1051009640 | H47: =H34+H37 -> 1106855001 | I47: =I34+I37 -> 1159876109
A48: （計算用）従業員1人当たり人件費（法定福利費等込み） | B48: =(B33-B34)/B42 -> 5283345.7 | C48: =B48*(1+C$4) -> 5441846.1 | D48: =C48*(1+D$4) -> 5605101.5 | E48: =D48*(1+E$4) -> 5801280 | F48: =E48*(1+F$4) -> 6004324.8 | G48: =F48*(1+G$4) -> 6214476.2 | H48: =G48*(1+H$4) -> 6431982.9 | I48: =H48*(1+I$4) -> 6657102.3
A49: （端数対策）全月分1人当たり給与の上乗せ率 | B49: 0.0002
A50: 【算出根拠1】売上高（①） 2026年3月期実績11,168,904,537円を起点とする。進行期・基準年度は設備導入前で、価格転嫁による小幅な伸び（各+1.5%）にとどめる。1年目は装置の通年稼働で遅番の投入担当が不要になり、17.5時間稼働が安定するため、キャパ不足で断っていた約4億円規模の案件（年間800万袋×50円）を取り込み+4.0%（+460百万円。案件と価格転嫁の範囲内）とする。2年目は多能工化したパートが遅番オペレーターを担い、日勤に戻った社員が提案型ODM（機能性・介護・防災向け）を獲得、3年目はその定着を見込み、各+4.0%とする。目標値として策定する4・5年目も各+4.0%とする。年+4.0%は清涼飲料の生産者販売金額の伸び（2025年+5.3%）を下回る保守的な水準であり、Eライン横展開の効果は織り込まない。
A55: 【算出根拠2】売上原価 売上原価は、原価内の人件費・減価償却費を含む総額を「売上高×原価率」で計算する。原価率は2026年3月期実績90.59%→進行期90.57%→基準年度90.50%（価格転嫁でわずかに改善）→1年目90.25%→2年目90.00%→3年目89.75%（年0.25pt改善）とする。目標値として策定する4・5年目は、ODM比率の上昇が定着して年0.30pt改善し89.45%→89.15%とする。改善の理由は、①省力化による労務費の抑制（別紙３の労働時間削減額9,047,144円／年＝売上比約0.08pt）、②利益率の高い提案型ODM（小売PB商品の例：売価56円／原価44円）の比率向上、③価格転嫁の進展である。原価内の人件費（人件費計を2026年3月期の比率71.8%で按分）と減価償却費（本設備9,200,000円／年は原価に計上）の増加は総額に含め、材料費等の比率低下で吸収する前提である。
A60: 【算出根拠3】販管費 販管費＝販管費内の人件費＋販管費内の減価償却費＋その他販管費。販管費内の人件費は人件費計から原価内分を差し引いた額（2026年3月期の比率28.2%。役員報酬65,655,000円を含む）、販管費内の減価償却費は24,831,635円で横ばい、その他販管費は2026年3月期実績の売上高比4.77%（532,780,738円÷11,168,904,537円）を維持する。
A65: 【算出根拠4】人件費・1人当たり給与支給総額 人件費（法定福利費・福利厚生費・退職金を含む）は、2026年3月期の従業員1人当たり人件費5,283,346円（(1,021,940,577円−役員報酬65,655,000円)÷181名）に、1人当たり賃上げ率（足下3.0%、基準年度以降3.5%）を毎年乗じ、常勤従業員数（177→181→184→188→191名、4・5年目は195・198名。年3〜4名の新卒採用、退職は見込まない）を掛けて、役員報酬65,655,000円（据え置き）を加えて積算する。全月分の給与等の支給を受けた従業員の1人当たり給与支給総額は、2026年3月期4,319,298円（717,003,483円÷166名）を起点に同じ賃上げ率で引き上げ（様式の切捨て計算で要件を割り込まないよう0.02%を上乗せ）、基準年度4,584,175円→3年目5,085,606円（5年目5,450,006円）とする。全月分の従業員数は常勤従業員数と同数とし、給与支給総額＝1人当たり×人数（基準年度829,735,675円→3年目971,350,746円）。
A70: 【算出根拠5】減価償却費 既存設備の減価償却費は更新投資で維持されると仮定し、2026年3月期実績298,864,468円（原価内274,032,833円、販管費内24,831,635円）で横ばいとする。本事業の設備92,000,000円（税抜）は定額法・耐用年数10年で9,200,000円／年を、通年稼働となる1年目（2029年3月期）から売上原価に計上する（4・5年目も同額。基準年度は稼働が約2か月で、別紙４にも入力欄がないため計上しない）。
A75: 【算出根拠6】付加価値額・労働生産性と必須要件の達成状況 付加価値額＝営業利益＋人件費＋減価償却費。基準年度1,593,327,430円→3年目1,891,288,147円（+297,960,717円、年平均成長率5.88%）。労働生産性＝付加価値額÷（役員7名＋常勤従業員数）で、基準年度8,475,145.90円→3年目9,551,960.33円。年平均成長率は1年目4.53%・2年目4.10%・3年目4.06%で、毎年、要件4.0%以上を満たす。1人当たり給与支給総額の年平均成長率は、足下（2026年3月期→基準年度）3.02%（要件3.0%以上）、基準年度→3年目3.52%（要件3.5%以上）。目標値として策定する4・5年目は、付加価値額2,008,310,651円・2,127,257,599円、労働生産性の年平均成長率4.07%・4.13%、1人当たり給与支給総額3.52%で、5年目まで要件を上回る。成長率はいずれも別紙４と同じく小数第3位を切り捨てた値。労働分配率は2026年3月期67.0%→基準年度67.8%→3年目66.2%と推移し、賃上げと収益性を両立する。
A80: 労働生産性（付加価値額÷（従業員＋役員）） | B80: =ROUNDDOWN(B41/(B42+B46),2) -> 8115043 | C80: =ROUNDDOWN(C41/(C42+C46),2) -> 8372438 | D80: =ROUNDDOWN(D41/(D42+D46),2) -> 8475145.9 | E80: =ROUNDDOWN(E41/(E42+E46),2) -> 8859578.6 | F80: =ROUNDDOWN(F41/(F42+F46),2) -> 9185485.9 | G80: =ROUNDDOWN(G41/(G42+G46),2) -> 9551960.3 | H80: =ROUNDDOWN(H41/(H42+H46),2) -> 9942131.9 | I80: =ROUNDDOWN(I41/(I42+I46),2) -> 10376866
A81: 【要件確認】付加価値額の年平均成長率（基準年度比） | E81: =ROUNDDOWN(((E41/$D$41)^(1/(COLUMN(E41)-COLUMN($D$41)))-1)*100,2)/100 -> 0.062 | F81: =ROUNDDOWN(((F41/$D$41)^(1/(COLUMN(F41)-COLUMN($D$41)))-1)*100,2)/100 -> 0.0602 | G81: =ROUNDDOWN(((G41/$D$41)^(1/(COLUMN(G41)-COLUMN($D$41)))-1)*100,2)/100 -> 0.0588 | H81: =ROUNDDOWN(((H41/$D$41)^(1/(COLUMN(H41)-COLUMN($D$41)))-1)*100,2)/100 -> 0.0595 | I81: =ROUNDDOWN(((I41/$D$41)^(1/(COLUMN(I41)-COLUMN($D$41)))-1)*100,2)/100 -> 0.0595
A82: 【要件確認】労働生産性の年平均成長率（基準年度比・要件4.0%以上） | E82: =ROUNDDOWN(((E80/$D$80)^(1/(COLUMN(E80)-COLUMN($D$80)))-1)*100,2)/100 -> 0.0453 | F82: =ROUNDDOWN(((F80/$D$80)^(1/(COLUMN(F80)-COLUMN($D$80)))-1)*100,2)/100 -> 0.041 | G82: =ROUNDDOWN(((G80/$D$80)^(1/(COLUMN(G80)-COLUMN($D$80)))-1)*100,2)/100 -> 0.0406 | H82: =ROUNDDOWN(((H80/$D$80)^(1/(COLUMN(H80)-COLUMN($D$80)))-1)*100,2)/100 -> 0.0407 | I82: =ROUNDDOWN(((I80/$D$80)^(1/(COLUMN(I80)-COLUMN($D$80)))-1)*100,2)/100 -> 0.0413
A83: 【要件確認】1人当たり給与の年平均成長率（足下・要件3.0%以上） | C83: =ROUNDDOWN(((C45/$B$45)^(1/(COLUMN(C45)-COLUMN($B$45)))-1)*100,2)/100 -> 0.0302 | D83: =ROUNDDOWN(((D45/$B$45)^(1/(COLUMN(D45)-COLUMN($B$45)))-1)*100,2)/100 -> 0.0302
A84: 【要件確認】1人当たり給与支給総額の年平均成長率（基準年度比・要件3.5%以上） | E84: =ROUNDDOWN(((E45/$D$45)^(1/(COLUMN(E45)-COLUMN($D$45)))-1)*100,2)/100 -> 0.0352 | F84: =ROUNDDOWN(((F45/$D$45)^(1/(COLUMN(F45)-COLUMN($D$45)))-1)*100,2)/100 -> 0.0352 | G84: =ROUNDDOWN(((G45/$D$45)^(1/(COLUMN(G45)-COLUMN($D$45)))-1)*100,2)/100 -> 0.0352 | H84: =ROUNDDOWN(((H45/$D$45)^(1/(COLUMN(H45)-COLUMN($D$45)))-1)*100,2)/100 -> 0.0352 | I84: =ROUNDDOWN(((I45/$D$45)^(1/(COLUMN(I45)-COLUMN($D$45)))-1)*100,2)/100 -> 0.0352
A85: （参考）労働分配率（人件費÷付加価値額） | B85: =B33/B41 -> 0.66984908 | C85: =C33/C41 -> 0.66786282 | D85: =D33/D41 -> 0.67793873 | E85: =E33/E41 -> 0.66960421 | F85: =F33/F41 -> 0.6668648 | G85: =G33/G41 -> 0.66231048 | H85: =H33/H41 -> 0.65721489 | I85: =I33/I41 -> 0.65049068
A86: （参考）増加した付加価値額（各年度−基準年度）※3年目の値を別紙３に入力 | E86: =E41-$D$41 -> 98852087 | F86: =F41-$D$41 -> 197842325 | G86: =G41-$D$41 -> 297960717 | H86: =H41-$D$41 -> 414983221 | I86: =I41-$D$41 -> 533930169

Sheet 人件費・給与支給総額
C1: 2026年3月期
A3: 原価内 | B3: 賃金（労務費内） | C3: 376769793 | J3: 2026年3月期
B4: 雑給 | C4: 61352644 | I4: ①売上高 | J4: 11168904537
B5: 賞与 | C5: 153907318
B6: 研究開発労務費 | C6: 28319705 | I6: 売上原価 | J6: 10117780260 | K6: =J6/J4 -> 0.90588833
B7: 法定福利費 | C7: 91831558 | I7: 内減価償却費 | J7: =J11 -> 274032833
B8: 厚生費 | C8: 21070705 | I8: 減価償却費を除いた売上原価 | J8: =J6-J7 -> 9843747427 | K8: =J8/$J$4 -> 0.88135299
I9: 売上原価内人件費と売上原価内減価償却を除いた売上原価 | J9: =J6-J11-C10 -> 9110495704 | K9: =J9/$J$4 -> 0.81570182
B10: 売上原価内人件費 | C10: =C3+C4+C5+C6+C7+C8 -> 733251723
B11: └うち役員給与支給総額 | C11: =C12+C13 -> 0 | I11: 売上原価内減価償却費 | J11: 274032833
B12: └うち賞与 | C12: 0 | I12: 販管費内減価償却費 | J12: 24831635
B13: └うち給料・賃金 | C13: 0 | I13: 減価償却費計 | J13: =J11+J12 -> 298864468
B14: └うち従業員給与支給総額 | C14: =C15+C16 -> 620349460
B15: └うち賞与 | C15: =C5 -> 153907318
B16: └うち給料・賃金 | C16: =C3+C4+C6 -> 466442142
C18: 人件費 | D18: 給与支給総額
A19: 販管費 | B19: 給与手当 | C19: 120356805 | D19: 120356805
B20: 雑給 | C20: 2987000 | D20: 2987000
B21: 役員報酬 | C21: 65655000 | D21: 65655000
B22: 役員賞与 | C22: 0 | D22: 0
B23: 従業員賞与 | C23: 50163729 | D23: 50163729
B24: 法定福利費 | C24: 35845218
B25: 厚生費 | C25: 11607582
B26: 退職金 | C26: 2073520
B28: 販管費内人件費 | C28: =C19+C20+C21+C22+C23+C24+C25+C26 -> 288688854
B29: └うち役員給与支給総額 | C29: =C30+C31 -> 65655000 | D29: =D30+D31 -> 65655000
B30: └うち賞与 | C30: =C22 -> 0 | D30: =D22 -> 0
B31: └うち給料・賃金 | C31: =C21 -> 65655000 | D31: =D21 -> 65655000
B32: └うち従業員給与支給総額 | C32: =C33+C34 -> 173507534 | D32: =D33+D34 -> 173507534
B33: └うち賞与 | C33: =C23 -> 50163729 | D33: =D23 -> 50163729
B34: └うち給料・賃金 | C34: =C19+C20 -> 123343805 | D34: =D19+D20 -> 123343805
B36: 売上原価＋販管費人件費合計 | C36: =C28+C10 -> 1021940577
B37: └うち役員給与支給総額 | C37: =C29+C11 -> 65655000 | D37: =D29+D11 -> 65655000
B38: └うち賞与 | C38: =C30+C12 -> 0 | D38: =D30+D12 -> 0
B39: └うち給料・賃金 | C39: =C31+C13 -> 65655000 | D39: =D31+D13 -> 65655000
B40: └うち従業員給与支給総額 | C40: =C32+C14 -> 793856994 | D40: =D32+D14 -> 173507534
B41: └うち賞与 | C41: =C33+C15 -> 204071047 | D41: =D33+D15 -> 50163729
B42: └うち給料・賃金 | C42: =C34+C16 -> 589785947 | D42: =D34+D16 -> 123343805
